_wiringpi.cpython-37m-arm-linux-gnueabihf.so
wiringpi.py
wiringpi-2.60.0.dist-info/LICENSE.txt
wiringpi-2.60.0.dist-info/METADATA
wiringpi-2.60.0.dist-info/WHEEL
wiringpi-2.60.0.dist-info/top_level.txt
wiringpi-2.60.0.dist-info/RECORD
